nwu_cards_demo/__init__.py
nwu_cards_demo/_nbdev.py
nwu_cards_demo/card.py
nwu_cards_demo/deck.py
nwu_cards_demo-0.0.2.dist-info/LICENSE
nwu_cards_demo-0.0.2.dist-info/METADATA
nwu_cards_demo-0.0.2.dist-info/WHEEL
nwu_cards_demo-0.0.2.dist-info/entry_points.txt
nwu_cards_demo-0.0.2.dist-info/top_level.txt
nwu_cards_demo-0.0.2.dist-info/RECORD
