Metadata-Version: 2.1
Name: nwu-cards-demo
Version: 0.0.2
Summary: A demo of nbdev
Home-page: https://github.com/hamelsmu/nwu_cards_demo/tree/master/
Author: Hamel Husain
Author-email: hamel@example.com
License: Apache Software License 2.0
Keywords: nbdev
Platform: UNKNOWN
Classifier: Development Status :: 3 - Alpha
Classifier: Intended Audience :: Developers
Classifier: License :: OSI Approved :: Apache Software License
Classifier: Natural Language :: English
Classifier: Programming Language :: Python :: 3.6
Classifier: Programming Language :: Python :: 3.7
Classifier: Programming Language :: Python :: 3.8
Requires-Python: >=3.6
